ml_proj_init/__init__.py
ml_proj_init/__main__.py
ml_proj_init/config.py
ml_proj_init/utils.py
ml_proj_init/validation.py
ml_proj_init/data/dl/Dockerfile
ml_proj_init/data/dl/LICENSE
ml_proj_init/data/dl/MANIFEST.in
ml_proj_init/data/dl/README.md
ml_proj_init/data/dl/requirements.txt
ml_proj_init/data/dl/setup.py
ml_proj_init/data/dl/data/links.json
ml_proj_init/data/dl/src/__init__.py
ml_proj_init/data/dl/src/__main__.py
ml_proj_init/data/dl/src/dataset/dataloader.py
ml_proj_init/data/dl/src/dataset/prepare_dataset.py
ml_proj_init/data/dl/src/dataset/preprocess_dataset.py
ml_proj_init/data/dl/src/features/generate_features.py
ml_proj_init/data/dl/src/models/predict_model.py
ml_proj_init/data/dl/src/models/train_model.py
ml_proj_init/data/dl/src/visualize/visualize_dataset.py
ml_proj_init/data/dl/src/visualize/visualize_features.py
ml_proj_init/data/dl/src/visualize/visualize_performance.py
ml_proj_init/data/loader/csv_loader.py
ml_proj_init/data/loader/img_loader.py
ml_proj_init/data/loader/text_loader.py
ml_proj_init/data/ml/Dockerfile
ml_proj_init/data/ml/LICENSE
ml_proj_init/data/ml/MANIFEST.in
ml_proj_init/data/ml/README.md
ml_proj_init/data/ml/requirements.txt
ml_proj_init/data/ml/setup.py
ml_proj_init/data/ml/data/links.json
ml_proj_init/data/ml/src/__init__.py
ml_proj_init/data/ml/src/__main__.py
ml_proj_init/data/ml/src/dataset/dataloader.py
ml_proj_init/data/ml/src/dataset/prepare_dataset.py
ml_proj_init/data/ml/src/dataset/preprocess_dataset.py
ml_proj_init/data/ml/src/features/generate_features.py
ml_proj_init/data/ml/src/models/predict_model.py
ml_proj_init/data/ml/src/models/train_model.py
ml_proj_init/data/ml/src/visualize/visualize_dataset.py
ml_proj_init/data/ml/src/visualize/visualize_features.py
ml_proj_init/data/ml/src/visualize/visualize_performance.py
ml_proj_init/data/network/cnn_nn.py
ml_proj_init/data/network/lstm_nn.py
ml_proj_init/data/network/nn_nn.py
ml_proj_init-1.0.3.dist-info/LICENSE
ml_proj_init-1.0.3.dist-info/METADATA
ml_proj_init-1.0.3.dist-info/WHEEL
ml_proj_init-1.0.3.dist-info/entry_points.txt
ml_proj_init-1.0.3.dist-info/top_level.txt
ml_proj_init-1.0.3.dist-info/RECORD
