Metadata-Version: 2.1
Name: ml-proj-init
Version: 1.0.3
Summary: Machine learning and Deep learning project structure initializer
Home-page: https://github.com/faruk-ahmad/ml-proj-init
Author: faruk-ahmad
Author-email: faruk.csebrur@gmail.com
License: UNKNOWN
Platform: UNKNOWN
Classifier: Programming Language :: Python :: 3
Classifier: License :: OSI Approved :: MIT License
Classifier: Operating System :: OS Independent
Requires-Python: >=3.5
